movoid_threading/__init__.py
movoid_threading/thread.py
movoid_threading-1.0.2.dist-info/METADATA
movoid_threading-1.0.2.dist-info/WHEEL
movoid_threading-1.0.2.dist-info/top_level.txt
movoid_threading-1.0.2.dist-info/RECORD
